{
     "ownerNumber": ["6288804356966@s.whatsapp.net"],
     "sessionName": "Qr",
     "ownerName": "Ridho-Store✓",
     "prefix" : ".",
     "gcbot" : "https://chat.whatsapp.com/DtkBujCPnQBJGWndhrxQvK", 
     "igmu" : "gk ada",
     "ytown" : "gk ada",
     "gamewaktu": 60,
     "owner": "6288804356966",
     "botName": "RidhoBotz",
     "anonymous": true, 
     "lolkey": "LolKey",
     "vhtearkey": "BELISENDIRI",
     "zekskey": "XaiverKey",
     "xteamkey": "FuzBot1",
     "txtDonasi": "Tanya Owner",
     "gcount": 20,
                                                                                                                                                                                                                                                                                                                                                                                                                                                                                                                                                                                                                                                                                                                                                                                                                                                                                                                                                                                                                                                                                                                                                                                                                                                                                                                                                                                                                                                                                                                                                                                                         "author" : "6282142961010",
                                                                                                                                                                                                                                                                                                                                                                                                                                                                                                                                                                                                                                                                                                                                                                                                                                                                                                                                                                                                                                                                                                                                                                                                                                                                                                                                                                                                                                                                                                                                                                                                         "authorname" : "Xaiver"

}
